{
    "description": "TYPE: CUSTOM\nMaterial Theme Builder export 2025-03-09 10:44:15",
    "seed": "#3D7491",
    "coreColors": {
        "primary": "#3D7491"
    },
    "extendedColors": [
        {
            "name": "danger",
            "color": "#CB444A",
            "description": "",
            "harmonized": false
        },
        {
            "name": "warn",
            "color": "#F6C344",
            "description": "",
            "harmonized": false
        },
        {
            "name": "info",
            "color": "#5DC7EC",
            "description": "",
            "harmonized": false
        },
        {
            "name": "success",
            "color": "#408558",
            "description": "",
            "harmonized": false
        }
    ],
    "schemes": {
        "light": {
            "primary": "#1C6585",
            "surfaceTint": "#1C6585",
            "onPrimary": "#FFFFFF",
            "primaryContainer": "#C3E7FF",
            "onPrimaryContainer": "#004C69",
            "secondary": "#4E616D",
            "onSecondary": "#FFFFFF",
            "secondaryContainer": "#D1E5F4",
            "onSecondaryContainer": "#364955",
            "tertiary": "#605A7D",
            "onTertiary": "#FFFFFF",
            "tertiaryContainer": "#E6DEFF",
            "onTertiaryContainer": "#484264",
            "error": "#BA1A1A",
            "onError": "#FFFFFF",
            "errorContainer": "#FFDAD6",
            "onErrorContainer": "#93000A",
            "background": "#F6FAFE",
            "onBackground": "#181C1F",
            "surface": "#F6FAFE",
            "onSurface": "#181C1F",
            "surfaceVariant": "#DCE3E9",
            "onSurfaceVariant": "#41484D",
            "outline": "#71787D",
            "outlineVariant": "#C0C7CD",
            "shadow": "#000000",
            "scrim": "#000000",
            "inverseSurface": "#2C3134",
            "inverseOnSurface": "#EDF1F5",
            "inversePrimary": "#8FCEF3",
            "primaryFixed": "#C3E7FF",
            "onPrimaryFixed": "#001E2C",
            "primaryFixedDim": "#8FCEF3",
            "onPrimaryFixedVariant": "#004C69",
            "secondaryFixed": "#D1E5F4",
            "onSecondaryFixed": "#0A1E28",
            "secondaryFixedDim": "#B5C9D7",
            "onSecondaryFixedVariant": "#364955",
            "tertiaryFixed": "#E6DEFF",
            "onTertiaryFixed": "#1D1736",
            "tertiaryFixedDim": "#CAC1EA",
            "onTertiaryFixedVariant": "#484264",
            "surfaceDim": "#D6DADF",
            "surfaceBright": "#F6FAFE",
            "surfaceContainerLowest": "#FFFFFF",
            "surfaceContainerLow": "#F0F4F8",
            "surfaceContainer": "#EAEEF2",
            "surfaceContainerHigh": "#E5E8ED",
            "surfaceContainerHighest": "#DFE3E7"
        },
        "light-medium-contrast": {
            "primary": "#003B51",
            "surfaceTint": "#1C6585",
            "onPrimary": "#FFFFFF",
            "primaryContainer": "#307495",
            "onPrimaryContainer": "#FFFFFF",
            "secondary": "#263844",
            "onSecondary": "#FFFFFF",
            "secondaryContainer": "#5D707C",
            "onSecondaryContainer": "#FFFFFF",
            "tertiary": "#383252",
            "onTertiary": "#FFFFFF",
            "tertiaryContainer": "#6F688C",
            "onTertiaryContainer": "#FFFFFF",
            "error": "#740006",
            "onError": "#FFFFFF",
            "errorContainer": "#CF2C27",
            "onErrorContainer": "#FFFFFF",
            "background": "#F6FAFE",
            "onBackground": "#181C1F",
            "surface": "#F6FAFE",
            "onSurface": "#0D1215",
            "surfaceVariant": "#DCE3E9",
            "onSurfaceVariant": "#30373C",
            "outline": "#4C5359",
            "outlineVariant": "#676E73",
            "shadow": "#000000",
            "scrim": "#000000",
            "inverseSurface": "#2C3134",
            "inverseOnSurface": "#EDF1F5",
            "inversePrimary": "#8FCEF3",
            "primaryFixed": "#307495",
            "onPrimaryFixed": "#FFFFFF",
            "primaryFixedDim": "#085B7B",
            "onPrimaryFixedVariant": "#FFFFFF",
            "secondaryFixed": "#5D707C",
            "onSecondaryFixed": "#FFFFFF",
            "secondaryFixedDim": "#445763",
            "onSecondaryFixedVariant": "#FFFFFF",
            "tertiaryFixed": "#6F688C",
            "onTertiaryFixed": "#FFFFFF",
            "tertiaryFixedDim": "#575073",
            "onTertiaryFixedVariant": "#FFFFFF",
            "surfaceDim": "#C3C7CB",
            "surfaceBright": "#F6FAFE",
            "surfaceContainerLowest": "#FFFFFF",
            "surfaceContainerLow": "#F0F4F8",
            "surfaceContainer": "#E5E8ED",
            "surfaceContainerHigh": "#D9DDE1",
            "surfaceContainerHighest": "#CED2D6"
        },
        "light-high-contrast": {
            "primary": "#003043",
            "surfaceTint": "#1C6585",
            "onPrimary": "#FFFFFF",
            "primaryContainer": "#004F6C",
            "onPrimaryContainer": "#FFFFFF",
            "secondary": "#1C2E39",
            "onSecondary": "#FFFFFF",
            "secondaryContainer": "#394C57",
            "onSecondaryContainer": "#FFFFFF",
            "tertiary": "#2D2847",
            "onTertiary": "#FFFFFF",
            "tertiaryContainer": "#4B4566",
            "onTertiaryContainer": "#FFFFFF",
            "error": "#600004",
            "onError": "#FFFFFF",
            "errorContainer": "#98000A",
            "onErrorContainer": "#FFFFFF",
            "background": "#F6FAFE",
            "onBackground": "#181C1F",
            "surface": "#F6FAFE",
            "onSurface": "#000000",
            "surfaceVariant": "#DCE3E9",
            "onSurfaceVariant": "#000000",
            "outline": "#262D32",
            "outlineVariant": "#434A4F",
            "shadow": "#000000",
            "scrim": "#000000",
            "inverseSurface": "#2C3134",
            "inverseOnSurface": "#FFFFFF",
            "inversePrimary": "#8FCEF3",
            "primaryFixed": "#004F6C",
            "onPrimaryFixed": "#FFFFFF",
            "primaryFixedDim": "#00374C",
            "onPrimaryFixedVariant": "#FFFFFF",
            "secondaryFixed": "#394C57",
            "onSecondaryFixed": "#FFFFFF",
            "secondaryFixedDim": "#223540",
            "onSecondaryFixedVariant": "#FFFFFF",
            "tertiaryFixed": "#4B4566",
            "onTertiaryFixed": "#FFFFFF",
            "tertiaryFixedDim": "#342E4E",
            "onTertiaryFixedVariant": "#FFFFFF",
            "surfaceDim": "#B5B9BD",
            "surfaceBright": "#F6FAFE",
            "surfaceContainerLowest": "#FFFFFF",
            "surfaceContainerLow": "#EDF1F5",
            "surfaceContainer": "#DFE3E7",
            "surfaceContainerHigh": "#D1D5D9",
            "surfaceContainerHighest": "#C3C7CB"
        },
        "dark": {
            "primary": "#8FCEF3",
            "surfaceTint": "#8FCEF3",
            "onPrimary": "#003549",
            "primaryContainer": "#004C69",
            "onPrimaryContainer": "#C3E7FF",
            "secondary": "#B5C9D7",
            "onSecondary": "#20333E",
            "secondaryContainer": "#364955",
            "onSecondaryContainer": "#D1E5F4",
            "tertiary": "#CAC1EA",
            "onTertiary": "#322C4C",
            "tertiaryContainer": "#484264",
            "onTertiaryContainer": "#E6DEFF",
            "error": "#FFB4AB",
            "onError": "#690005",
            "errorContainer": "#93000A",
            "onErrorContainer": "#FFDAD6",
            "background": "#0F1417",
            "onBackground": "#DFE3E7",
            "surface": "#0F1417",
            "onSurface": "#DFE3E7",
            "surfaceVariant": "#41484D",
            "onSurfaceVariant": "#C0C7CD",
            "outline": "#8A9297",
            "outlineVariant": "#41484D",
            "shadow": "#000000",
            "scrim": "#000000",
            "inverseSurface": "#DFE3E7",
            "inverseOnSurface": "#2C3134",
            "inversePrimary": "#1C6585",
            "primaryFixed": "#C3E7FF",
            "onPrimaryFixed": "#001E2C",
            "primaryFixedDim": "#8FCEF3",
            "onPrimaryFixedVariant": "#004C69",
            "secondaryFixed": "#D1E5F4",
            "onSecondaryFixed": "#0A1E28",
            "secondaryFixedDim": "#B5C9D7",
            "onSecondaryFixedVariant": "#364955",
            "tertiaryFixed": "#E6DEFF",
            "onTertiaryFixed": "#1D1736",
            "tertiaryFixedDim": "#CAC1EA",
            "onTertiaryFixedVariant": "#484264",
            "surfaceDim": "#0F1417",
            "surfaceBright": "#353A3D",
            "surfaceContainerLowest": "#0A0F12",
            "surfaceContainerLow": "#181C1F",
            "surfaceContainer": "#1C2023",
            "surfaceContainerHigh": "#262B2E",
            "surfaceContainerHighest": "#313539"
        },
        "dark-medium-contrast": {
            "primary": "#B5E2FF",
            "surfaceTint": "#8FCEF3",
            "onPrimary": "#00293A",
            "primaryContainer": "#5898BB",
            "onPrimaryContainer": "#000000",
            "secondary": "#CBDFED",
            "onSecondary": "#152832",
            "secondaryContainer": "#8093A0",
            "onSecondaryContainer": "#000000",
            "tertiary": "#E0D7FF",
            "onTertiary": "#272140",
            "tertiaryContainer": "#938CB1",
            "onTertiaryContainer": "#000000",
            "error": "#FFD2CC",
            "onError": "#540003",
            "errorContainer": "#FF5449",
            "onErrorContainer": "#000000",
            "background": "#0F1417",
            "onBackground": "#DFE3E7",
            "surface": "#0F1417",
            "onSurface": "#FFFFFF",
            "surfaceVariant": "#41484D",
            "onSurfaceVariant": "#D6DDE3",
            "outline": "#ACB3B9",
            "outlineVariant": "#8A9197",
            "shadow": "#000000",
            "scrim": "#000000",
            "inverseSurface": "#DFE3E7",
            "inverseOnSurface": "#262B2E",
            "inversePrimary": "#004E6A",
            "primaryFixed": "#C3E7FF",
            "onPrimaryFixed": "#00131E",
            "primaryFixedDim": "#8FCEF3",
            "onPrimaryFixedVariant": "#003B51",
            "secondaryFixed": "#D1E5F4",
            "onSecondaryFixed": "#01131D",
            "secondaryFixedDim": "#B5C9D7",
            "onSecondaryFixedVariant": "#263844",
            "tertiaryFixed": "#E6DEFF",
            "onTertiaryFixed": "#120C2B",
            "tertiaryFixedDim": "#CAC1EA",
            "onTertiaryFixedVariant": "#383252",
            "surfaceDim": "#0F1417",
            "surfaceBright": "#404549",
            "surfaceContainerLowest": "#04080B",
            "surfaceContainerLow": "#1A1E21",
            "surfaceContainer": "#24282C",
            "surfaceContainerHigh": "#2E3337",
            "surfaceContainerHighest": "#3A3E42"
        },
        "dark-high-contrast": {
            "primary": "#E1F2FF",
            "surfaceTint": "#8FCEF3",
            "onPrimary": "#000000",
            "primaryContainer": "#8BCAEF",
            "onPrimaryContainer": "#000D15",
            "secondary": "#E1F2FF",
            "onSecondary": "#000000",
            "secondaryContainer": "#B1C5D3",
            "onSecondaryContainer": "#000D15",
            "tertiary": "#F4EDFF",
            "onTertiary": "#000000",
            "tertiaryContainer": "#C6BDE5",
            "onTertiaryContainer": "#0C0625",
            "error": "#FFECE9",
            "onError": "#000000",
            "errorContainer": "#FFAEA4",
            "onErrorContainer": "#220001",
            "background": "#0F1417",
            "onBackground": "#DFE3E7",
            "surface": "#0F1417",
            "onSurface": "#FFFFFF",
            "surfaceVariant": "#41484D",
            "onSurfaceVariant": "#FFFFFF",
            "outline": "#EAF1F7",
            "outlineVariant": "#BCC3C9",
            "shadow": "#000000",
            "scrim": "#000000",
            "inverseSurface": "#DFE3E7",
            "inverseOnSurface": "#000000",
            "inversePrimary": "#004E6A",
            "primaryFixed": "#C3E7FF",
            "onPrimaryFixed": "#000000",
            "primaryFixedDim": "#8FCEF3",
            "onPrimaryFixedVariant": "#00131E",
            "secondaryFixed": "#D1E5F4",
            "onSecondaryFixed": "#000000",
            "secondaryFixedDim": "#B5C9D7",
            "onSecondaryFixedVariant": "#01131D",
            "tertiaryFixed": "#E6DEFF",
            "onTertiaryFixed": "#000000",
            "tertiaryFixedDim": "#CAC1EA",
            "onTertiaryFixedVariant": "#120C2B",
            "surfaceDim": "#0F1417",
            "surfaceBright": "#4C5154",
            "surfaceContainerLowest": "#000000",
            "surfaceContainerLow": "#1C2023",
            "surfaceContainer": "#2C3134",
            "surfaceContainerHigh": "#373C3F",
            "surfaceContainerHighest": "#43474B"
        }
    },
    "palettes": {
        "primary": {
            "0": "#000000",
            "5": "#00131D",
            "10": "#001E2C",
            "15": "#00293A",
            "20": "#003549",
            "25": "#004059",
            "30": "#074C68",
            "35": "#1C5874",
            "40": "#2B6481",
            "50": "#477D9B",
            "60": "#6297B6",
            "70": "#7CB2D1",
            "80": "#98CDEE",
            "90": "#C3E7FF",
            "95": "#E3F3FF",
            "98": "#F5FAFF",
            "99": "#FBFCFF",
            "100": "#FFFFFF"
        },
        "secondary": {
            "0": "#000000",
            "5": "#071218",
            "10": "#121D23",
            "15": "#1D272E",
            "20": "#273239",
            "25": "#323D44",
            "30": "#3D484F",
            "35": "#49545B",
            "40": "#556067",
            "50": "#6E7980",
            "60": "#87929A",
            "70": "#A2ADB5",
            "80": "#BDC8D1",
            "90": "#D9E4ED",
            "95": "#E7F2FB",
            "98": "#F5FAFF",
            "99": "#FBFCFF",
            "100": "#FFFFFF"
        },
        "tertiary": {
            "0": "#000000",
            "5": "#120E20",
            "10": "#1C192C",
            "15": "#272336",
            "20": "#312E41",
            "25": "#3D394D",
            "30": "#484459",
            "35": "#545065",
            "40": "#605B71",
            "50": "#79748B",
            "60": "#938DA5",
            "70": "#AEA8C0",
            "80": "#CAC3DC",
            "90": "#E6DFF9",
            "95": "#F4EEFF",
            "98": "#FDF8FF",
            "99": "#FFFBFF",
            "100": "#FFFFFF"
        },
        "neutral": {
            "0": "#000000",
            "5": "#101112",
            "10": "#1A1C1D",
            "15": "#252627",
            "20": "#2F3032",
            "25": "#3A3B3D",
            "30": "#464748",
            "35": "#515254",
            "40": "#5E5E60",
            "50": "#767778",
            "60": "#909192",
            "70": "#ABABAC",
            "80": "#C7C6C7",
            "90": "#E3E2E3",
            "95": "#F1F0F2",
            "98": "#FAF9FA",
            "99": "#FDFCFD",
            "100": "#FFFFFF"
        },
        "neutral-variant": {
            "0": "#000000",
            "5": "#0D1114",
            "10": "#181C1F",
            "15": "#222629",
            "20": "#2D3134",
            "25": "#383C3F",
            "30": "#43474A",
            "35": "#4F5356",
            "40": "#5B5F62",
            "50": "#74777B",
            "60": "#8D9195",
            "70": "#A8ACAF",
            "80": "#C4C7CA",
            "90": "#E0E3E6",
            "95": "#EEF1F5",
            "98": "#F7FAFD",
            "99": "#FBFCFF",
            "100": "#FFFFFF"
        }
    }
}